renderer/__init__.py
renderer/utils/__init__.py
renderer/utils/constants.py
renderer/utils/formlib.py
renderer/utils/htmlib.py
renderer/utils/httplib.py
renderer/utils/money.py
renderer/utils/ocrlib.py
renderer/utils/quick.py
spider_renderer-0.2.3.dist-info/LICENSE
spider_renderer-0.2.3.dist-info/METADATA
spider_renderer-0.2.3.dist-info/WHEEL
spider_renderer-0.2.3.dist-info/top_level.txt
spider_renderer-0.2.3.dist-info/RECORD
