Metadata-Version: 2.1
Name: spider-renderer
Version: 0.2.3
Summary: Building a modular crawler template system based on Jinja2.
Home-page: https://github.com/ffujiawei/spider-renderer
Author: White Turing
Author-email: fu.jiawei@outlook.com
License: Apache 2.0
Keywords: spider,renderer,scrapy
Platform: UNKNOWN
Classifier: Intended Audience :: Developers
Classifier: License :: OSI Approved :: Apache Software License
Classifier: Operating System :: OS Independent
Classifier: Programming Language :: Python :: 3.6
Classifier: Programming Language :: Python :: 3.7
Classifier: Programming Language :: Python :: Implementation :: CPython
Classifier: Topic :: Software Development :: Libraries :: Python Modules
Requires-Python: >=3.6.0
Requires-Dist: requests
Requires-Dist: jinja2
